requirements.txt
idftools/01-verify_registry_windows.exe
idftools/02-create_new_registry_windows_runas.exe
idftools/Roboto-Regular.ttf
idftools/__init__.py
idftools/certificate.py
idftools/driversfactory.py
idftools/logging.conf
idftools/utilities.py
idftools-0.1.182.dist-info/METADATA
idftools-0.1.182.dist-info/WHEEL
idftools-0.1.182.dist-info/top_level.txt
idftools-0.1.182.dist-info/RECORD
