Metadata-Version: 2.1
Name: idftools
Version: 0.1.182
Summary: Um pacote com alguns utilitarios uteis
Home-page: https://github.com/eniodefarias/pypi-idftools
Author: eniodefarias
Author-email: eniodefarias@gmail.com
License: UNKNOWN
Platform: UNKNOWN
